flask_restful_patched-0.1.0.dist-info/METADATA
flask_restful_patched-0.1.0.dist-info/RECORD
flask_restful_patched-0.1.0.dist-info/WHEEL
flask_restful_patched-0.1.0.dist-info/top_level.txt
flask_restplus_patched/__init__.py
flask_restplus_patched/api.py
flask_restplus_patched/model.py
flask_restplus_patched/namespace.py
flask_restplus_patched/parameters.py
flask_restplus_patched/resource.py
flask_restplus_patched/swagger.py
